shazamctl/__init__.py
shazamctl-0.0.0a0.dist-info/WHEEL
shazamctl-0.0.0a0.dist-info/METADATA
shazamctl-0.0.0a0.dist-info/RECORD
