Metadata-Version: 2.1
Name: shazamctl
Version: 0.0.0a0
Summary: Open-source Shazam CLI
License: ISC
Author: Alexander Pushkov
Author-email: alexander@notpushk.in
Requires-Python: >=3.10,<4.0
Classifier: License :: OSI Approved
Classifier: Programming Language :: Python :: 3
Classifier: Programming Language :: Python :: 3.10
